obplatform/__init__.py
obplatform/connector.py
obplatform/logger.py
obplatform-1.1.0.dist-info/LICENSE
obplatform-1.1.0.dist-info/WHEEL
obplatform-1.1.0.dist-info/METADATA
obplatform-1.1.0.dist-info/RECORD
