Metadata-Version: 2.1
Name: obplatform
Version: 1.1.0
Summary: APIs to access ASHRAE OB Database
Author: Wei Mu
Author-email: wmu100@syr.edu
Requires-Python: >=3.7.1,<4.0
Classifier: License :: OSI Approved :: MIT License
Classifier: Operating System :: OS Independent
Classifier: Programming Language :: Python :: 3
Classifier: Programming Language :: Python :: 3.10
Classifier: Programming Language :: Python :: 3.7
Classifier: Programming Language :: Python :: 3.8
Classifier: Programming Language :: Python :: 3.9
Classifier: Topic :: Software Development :: Libraries :: Python Modules
Provides-Extra: pandas
Requires-Dist: pandas (>=1.3.4,<2.0.0); extra == "pandas"
Requires-Dist: requests (>=2.26.0,<3.0.0)
Requires-Dist: tqdm (>=4.62.3,<5.0.0)
Project-URL: Bug Tracker, https://github.com/umonaca/obplatform/issues
Project-URL: homepage, https://ashraeobdatabase.com
Project-URL: repository, https://github.com/umonaca/obplatform
